aleimi/__init__.py
aleimi/_version.py
aleimi/boltzmann.py
aleimi/cli.py
aleimi/confgen.py
aleimi/extractor.py
aleimi/processed.py
aleimi/templates.py
aleimi/utils.py
aleimi-0.0.2.dist-info/LICENSE
aleimi-0.0.2.dist-info/METADATA
aleimi-0.0.2.dist-info/WHEEL
aleimi-0.0.2.dist-info/entry_points.txt
aleimi-0.0.2.dist-info/top_level.txt
aleimi-0.0.2.dist-info/RECORD
