Metadata-Version: 2.1
Name: aleimi
Version: 0.0.2
Summary: Stochastic Conformation Analysis at semi empirical level with ab initio refinement for small molecules
Author-email: Alejandro Martínez-León <ale94mleon@gmail.com>
Project-URL: Hompage, https://github.com/ale94mleon/aleimi
Project-URL: Discussions, https://github.com/ale94mleon/aleimi/discussions
Project-URL: Documentation, https://aleimi.readthedocs.io/en/latest/
Project-URL: Issues, https://github.com/ale94mleon/aleimi/issues
Keywords: science,chemistry,biology,drug-design
Classifier: Development Status :: 2 - Pre-Alpha
Classifier: Operating System :: POSIX :: Linux
Classifier: Intended Audience :: Science/Research
Classifier: License :: OSI Approved :: Apache Software License
Classifier: Programming Language :: Python :: 3
Classifier: Programming Language :: Python :: 3.8
Classifier: Programming Language :: Python :: 3.9
Classifier: Programming Language :: Python :: 3.10
Classifier: Programming Language :: Python :: 3.11
Classifier: Topic :: Scientific/Engineering :: Bio-Informatics
Classifier: Topic :: Scientific/Engineering :: Chemistry
Classifier: Topic :: Scientific/Engineering :: Physics
Requires-Python: >=3.8
License-File: LICENSE
Requires-Dist: numpy
Requires-Dist: pandas
Requires-Dist: rdkit
Requires-Dist: rmsd
Requires-Dist: pyyaml
Provides-Extra: test
Requires-Dist: pytest ; extra == 'test'
Requires-Dist: pytest-cov ; extra == 'test'
